neuroneq/__init__.py
neuroneq/cli.py
neuroneq/main.py
neuroneq/utils.py
neuroneq-0.0.6.dist-info/LICENSE
neuroneq-0.0.6.dist-info/METADATA
neuroneq-0.0.6.dist-info/WHEEL
neuroneq-0.0.6.dist-info/entry_points.txt
neuroneq-0.0.6.dist-info/top_level.txt
neuroneq-0.0.6.dist-info/RECORD
