Metadata-Version: 2.1
Name: neuroneq
Version: 0.0.6
Summary: NeuronEQ
Home-page: https://github.com/tjbanks/neuroneq
Download-URL: 
Author: Tyler Banks
Author-email: tbanks@mail.missouri.edu
License: MIT
Classifier: Intended Audience :: Developers
Classifier: Intended Audience :: Education
Classifier: Intended Audience :: Science/Research
Classifier: License :: OSI Approved :: MIT License
Classifier: Programming Language :: Python :: 3
Classifier: Programming Language :: Python :: 3.6
Classifier: Topic :: Software Development :: Libraries
Classifier: Topic :: Software Development :: Libraries :: Python Modules
Classifier: Operating System :: OS Independent
License-File: LICENSE
Requires-Dist: click
Requires-Dist: matplotlib
Requires-Dist: numpy
Requires-Dist: scipy
Requires-Dist: sympy
